jsonline/__init__.py
jsonline/jsonline.py
jsonline-0.3.0.dist-info/WHEEL
jsonline-0.3.0.dist-info/METADATA
jsonline-0.3.0.dist-info/RECORD
