Metadata-Version: 2.3
Name: jsonline
Version: 0.3.0
Summary: Jsonline is intend to use to explore and work with json lines files and avoid keep the entire data in memory or constantly read the whole file
Author: fsadannn
Author-email: fsadannn <fsadannn@gmail.com>
License: MIT License
Requires-Dist: orjson>=3.11.1
Requires-Python: >=3.11
